streamlit_ai_assist/__init__.py
streamlit_ai_assist/example.py
streamlit_ai_assist/graphing.py
streamlit_ai_assist/backend/__init__.py
streamlit_ai_assist/backend/agents/__init__.py
streamlit_ai_assist/backend/agents/conversational_agent.py
streamlit_ai_assist/backend/agents/data_analyst_agent.py
streamlit_ai_assist/backend/agents/function_rewrite_agent.py
streamlit_ai_assist/backend/agents/llm.py
streamlit_ai_assist/backend/agents/prompts/__init__.py
streamlit_ai_assist/backend/agents/prompts/conversational_prompt.py
streamlit_ai_assist/backend/agents/prompts/data_analyst_prompt.py
streamlit_ai_assist/backend/agents/prompts/function_rewrite_prompt.py
streamlit_ai_assist/backend/data/__init__.py
streamlit_ai_assist/backend/data/database_connection.py
streamlit_ai_assist/backend/documents/__init__.py
streamlit_ai_assist/backend/documents/docs_to_function_names.py
streamlit_ai_assist/backend/documents/python_to_docs.py
streamlit_ai_assist/backend/github/__init__.py
streamlit_ai_assist/backend/github/repo_actions.py
streamlit_ai_assist/backend/interface/__init__.py
streamlit_ai_assist/backend/interface/main.py
streamlit_ai_assist/backend/interface/renderable.py
streamlit_ai_assist/backend/retrieval/__init__.py
streamlit_ai_assist/backend/retrieval/retrieve_top_k.py
streamlit_ai_assist/backend/tools/__init__.py
streamlit_ai_assist/backend/tools/base.py
streamlit_ai_assist/backend/tools/graph_tool.py
streamlit_ai_assist/backend/tools/new_graph_tool.py
streamlit_ai_assist/backend/tools/schema_tool.py
streamlit_ai_assist/backend/tools/show_tables_tool.py
streamlit_ai_assist/backend/tools/show_unique_tool.py
streamlit_ai_assist/backend/tools/sql_tool.py
streamlit_ai_assist/frontend/build/asset-manifest.json
streamlit_ai_assist/frontend/build/bootstrap.min.css
streamlit_ai_assist/frontend/build/index.html
streamlit_ai_assist/frontend/build/static/css/main.00e66aec.css
streamlit_ai_assist/frontend/build/static/css/main.00e66aec.css.map
streamlit_ai_assist-0.1.1.dist-info/LICENSE
streamlit_ai_assist-0.1.1.dist-info/METADATA
streamlit_ai_assist-0.1.1.dist-info/WHEEL
streamlit_ai_assist-0.1.1.dist-info/top_level.txt
streamlit_ai_assist-0.1.1.dist-info/RECORD
