Metadata-Version: 2.1
Name: streamlit-ai-assist
Version: 0.1.1
Summary: A built in data analyst for your Streamlit app
Home-page: 
Author: Kaitlyn Hennacy
Author-email: kaitlynhennacy@gmail.com
Requires-Python: >=3.7
License-File: LICENSE
Requires-Dist: streamlit >=1.34.0
Requires-Dist: plotly >=5.22.0
Requires-Dist: pydantic >=2.7.1
Requires-Dist: pygithub >=2.3.0
Requires-Dist: replicate >=0.26.0
Requires-Dist: requests >=2.31.0
Requires-Dist: scipy >=1.13.0
Requires-Dist: snowflake-snowpark-python >=1.16.0
Requires-Dist: snowflake-sqlalchemy >=1.5.1
Requires-Dist: sqlalchemy >=1.4
Requires-Dist: transformers >=4.41.0
Requires-Dist: streamlit-mic-recorder
Requires-Dist: python-dateutil <=2.9.0
Provides-Extra: devel
Requires-Dist: wheel ; extra == 'devel'
Requires-Dist: pytest ==7.4.0 ; extra == 'devel'
Requires-Dist: playwright ==1.39.0 ; extra == 'devel'
Requires-Dist: requests ==2.31.0 ; extra == 'devel'
Requires-Dist: pytest-playwright-snapshot ==1.0 ; extra == 'devel'
Requires-Dist: pytest-rerunfailures ==12.0 ; extra == 'devel'
